{"service": "organizations", "region": "us-east-1", "profile": null, "operation": "ListAccounts", "response": {"Accounts": [{"Id": "066456136355", "Arn": "arn:aws:organizations::660456532861:account/o-hysntkvrrv/066456136355", "Email": "stage@pulpdigital.com", "Name": "Pulp Digital Prod AWS", "Status": "ACTIVE", "JoinedMethod": "CREATED", "JoinedTimestamp": "2020-07-02T13:29:38.978000+00:00"}, {"Id": "585757452633", "Arn": "arn:aws:organizations::660456532861:account/o-hysntkvrrv/585757452633", "Email": "prod@pulpdigital.com", "Name": "Pulp Digital Prod AWS", "Status": "ACTIVE", "JoinedMethod": "CREATED", "JoinedTimestamp": "2020-07-02T13:28:25.424000+00:00"}, {"Id": "243657062678", "Arn": "arn:aws:organizations::660456532861:account/o-hysntkvrrv/243657062678", "Email": "admin@pulpdigital.com", "Name": "Pulp Digital Admin AWS", "Status": "ACTIVE", "JoinedMethod": "CREATED", "JoinedTimestamp": "2020-07-03T07:18:21.853000+00:00"}, {"Id": "486810953182", "Arn": "arn:aws:organizations::660456532861:account/o-hysntkvrrv/486810953182", "Email": "kevin@pulpdigital.com", "Name": "made-from-console", "Status": "ACTIVE", "JoinedMethod": "CREATED", "JoinedTimestamp": "2020-07-02T15:49:41.935000+00:00"}, {"Id": "660456532861", "Arn": "arn:aws:organizations::660456532861:account/o-hysntkvrrv/660456532861", "Email": "root@pulpdigital.com", "Name": "Pulp Digital Root AWS", "Status": "ACTIVE", "JoinedMethod": "INVITED", "JoinedTimestamp": "2020-07-02T10:51:14.635000+00:00"}, {"Id": "091552628469", "Arn": "arn:aws:organizations::660456532861:account/o-hysntkvrrv/091552628469", "Email": "test@pulpdigital.com", "Name": "Pulp Digital Test AWS", "Status": "ACTIVE", "JoinedMethod": "CREATED", "JoinedTimestamp": "2020-07-03T07:18:01.024000+00:00"}, {"Id": "735480114154", "Arn": "arn:aws:organizations::660456532861:account/o-hysntkvrrv/735480114154", "Email": "dev@pulpdigital.com", "Name": "Pulp Digital Dev AWS", "Status": "ACTIVE", "JoinedMethod": "CREATED", "JoinedTimestamp": "2020-07-03T07:18:03.075000+00:00"}], "ResponseMetadata": {"RequestId": "defb21e2-f5b5-41d0-9a3e-b4bfc6945f08", "HTTPStatusCode": 200, "HTTPHeaders": {"x-amzn-requestid": "defb21e2-f5b5-41d0-9a3e-b4bfc6945f08", "content-type": "application/x-amz-json-1.1", "content-length": "1692", "date": "Wed, 06 Jan 2021 09:53:55 GMT"}, "RetryAttempts": 0}}}